[
  {
    "postId": 1,
    "id": 1,
    "title": "Step 1",
    "imageSrc": "images/blog/skateboard/skate-1.jpeg"
  },
  {
    "postId": 1,
    "id": 2,
    "title": "Step 2",
    "imageSrc": "images/blog/skateboard/skate-2.jpeg"
  },
  {
    "postId": 1,
    "id": 3,
    "title": "Step 3",
    "imageSrc": "images/blog/skateboard/skate-3.jpeg"
  },
  {
    "postId": 1,
    "id": 4,
    "title": "Step 4",
    "imageSrc": "images/blog/skateboard/skate-4.jpeg"
  },
  {
    "postId": 1,
    "id": 5,
    "title": "Step 5",
    "imageSrc": "images/blog/skateboard/skate-5.jpeg"
  },
  {
    "postId": 1,
    "id": 6,
    "title": "Step 6",
    "imageSrc": "images/blog/skateboard/skate-6.jpeg"
  }
]
